LICENSE
MANIFEST.in
README.md
requirements.txt
run_little_brother.py
run_little_brother_test_suite.py
run_little_brother_test_suite_no_venv.py
setup.py
little_brother/__init__.py
little_brother/admin_data_handler.py
little_brother/admin_event.py
little_brother/alembic.ini
little_brother/app.py
little_brother/app_control.py
little_brother/app_control_config_model.py
little_brother/base_view_handler.py
little_brother/client_device_handler.py
little_brother/client_info.py
little_brother/client_process_handler.py
little_brother/client_stats.py
little_brother/constants.py
little_brother/context_rule_handler.py
little_brother/db_migrations.py
little_brother/dependency_injection.py
little_brother/entity_forms.py
little_brother/event_handler.py
little_brother/german_vacation_context_rule_handler.py
little_brother/git.py
little_brother/git_metadata.py
little_brother/language.py
little_brother/login_mapping.py
little_brother/process_handler.py
little_brother/process_handler_manager.py
little_brother/process_info.py
little_brother/process_statistics.py
little_brother/prometheus.py
little_brother/rule_handler.py
little_brother/rule_override.py
little_brother/rule_result_info.py
little_brother/settings.py
little_brother/simple_context_rule_handlers.py
little_brother/token_handler.py
little_brother/user_locale_handler.py
little_brother/user_manager.py
little_brother/user_status.py
little_brother.egg-info/PKG-INFO
little_brother.egg-info/SOURCES.txt
little_brother.egg-info/dependency_links.txt
little_brother.egg-info/requires.txt
little_brother.egg-info/top_level.txt
little_brother/alembic/env.py
little_brother/alembic/versions/0a5c7b6ad27a_fb_issue_124.py
little_brother/alembic/versions/2f458b3a313e_add_max_activity_duration.py
little_brother/alembic/versions/647cf46033a9_initial_db_model_at_488c798.py
little_brother/alembic/versions/8802c76063af_add_uid_mapping.py
little_brother/alembic/versions/96ff8f93ef32_add_downtime_attributes.py
little_brother/alembic/versions/9713cef84918_userstatus_issue_130.py
little_brother/alembic/versions/__init__.py
little_brother/alembic/versions/a271817b1d64_issue_169.py
